[
  {
    "Name": "Jo\u00E3o Silva",
    "Email": "joao.silva@email.com",
    "PhoneNumber": "11987654321",
    "Status": 1,
    "Type": 1,
    "Balance": 2500.00,
    "IncomeAmount": 5000.00,
    "Limit": 10000.00,
    "AddicionalCreditLimit": 5000.00,
    "AddicionalCreditLimitStatus": 4,
    "Id": "550e8400-e29b-41d4-a716-446655440000",
    "CreatedAt": "2024-01-15T10:30:00Z",
    "UpdatedAt": "2024-01-15T10:30:00Z"
  },
  {
    "Name": "Maria Santos",
    "Email": "maria.santos@email.com",
    "PhoneNumber": "11987654322",
    "Status": 1,
    "Type": 2,
    "Balance": 800.00,
    "IncomeAmount": 3000.00,
    "Limit": 5000.00,
    "AddicionalCreditLimit": 2000.00,
    "AddicionalCreditLimitStatus": 1,
    "Id": "550e8400-e29b-41d4-a716-446655440001",
    "CreatedAt": "2024-01-16T14:20:00Z",
    "UpdatedAt": "2024-01-16T14:20:00Z"
  },
  {
    "Name": "Pedro Oliveira",
    "Email": "pedro.oliveira@email.com",
    "PhoneNumber": "11987654323",
    "Status": 2,
    "Type": 1,
    "Balance": 1500.00,
    "IncomeAmount": 4000.00,
    "Limit": 8000.00,
    "AddicionalCreditLimit": 3000.00,
    "AddicionalCreditLimitStatus": 3,
    "Id": "550e8400-e29b-41d4-a716-446655440002",
    "CreatedAt": "2024-01-17T09:15:00Z",
    "UpdatedAt": "2024-01-17T09:15:00Z"
  },
  {
    "Name": "Lucas Sidnei dos Santos",
    "Email": "lucas.sidnei32@gmail.com",
    "PhoneNumber": "41984854353",
    "Status": 1,
    "Type": 1,
    "Balance": 5000,
    "IncomeAmount": 5000,
    "Limit": 0.0,
    "AddicionalCreditLimit": 0.0,
    "AddicionalCreditLimitStatus": 4,
    "Id": "bfca164b-ea70-4aea-997e-5ad65ac0f062",
    "CreatedAt": "2025-08-22T23:14:18.1158678Z",
    "UpdatedAt": "2025-08-22T23:14:18.115868Z"
  },
  {
    "Name": "Lucas Sidnei dos Santos",
    "Email": "lucas.sidnei@gmail.com",
    "PhoneNumber": "41984854353",
    "Status": 1,
    "Type": 1,
    "Balance": 29340,
    "IncomeAmount": 29340,
    "Limit": 0.0,
    "AddicionalCreditLimit": 0.0,
    "AddicionalCreditLimitStatus": 4,
    "Id": "dd7a152f-eb19-4b0f-b7d3-697337908eeb",
    "CreatedAt": "2025-08-23T13:11:45.6216153Z",
    "UpdatedAt": "2025-08-23T13:11:45.6216155Z"
  },
  {
    "Name": "Lucas Sidnei dos Santos",
    "Email": "lucas.sidnei1@gmail.com",
    "PhoneNumber": "41984854353",
    "Status": 1,
    "Type": 1,
    "Balance": 29340,
    "IncomeAmount": 29340,
    "Limit": 0.0,
    "AddicionalCreditLimit": 0.0,
    "AddicionalCreditLimitStatus": 4,
    "Id": "9a71c6f2-31f7-4446-b5df-b918c87799cc",
    "CreatedAt": "2025-08-23T13:12:34.2636934Z",
    "UpdatedAt": "2025-08-23T13:12:34.2636935Z"
  },
  {
    "Name": "t",
    "Email": "l@sa",
    "PhoneNumber": "1234567890492",
    "Status": 1,
    "Type": 1,
    "Balance": 210291,
    "IncomeAmount": 210291,
    "Limit": 0.0,
    "AddicionalCreditLimit": 0.0,
    "AddicionalCreditLimitStatus": 4,
    "Id": "3118f304-6637-4ca6-a9b1-a07167dc2ea1",
    "CreatedAt": "2025-08-23T13:28:35.520683Z",
    "UpdatedAt": "2025-08-23T13:28:35.5206831Z"
  },
  {
    "Name": "lucas",
    "Email": "lucas@gmail.com",
    "PhoneNumber": "11999999999",
    "Status": 1,
    "Type": 1,
    "Balance": 11221,
    "IncomeAmount": 11221,
    "Limit": 0.0,
    "AddicionalCreditLimit": 0.0,
    "AddicionalCreditLimitStatus": 4,
    "Id": "0f54d700-be4f-4ae2-98e0-acfa70ae19ab",
    "CreatedAt": "2025-08-23T13:47:47.2773523Z",
    "UpdatedAt": "2025-08-23T13:47:47.2773525Z"
  }
]